easy_api_vk/__init__.py
easy_api_vk-1.2.dist-info/METADATA
easy_api_vk-1.2.dist-info/WHEEL
easy_api_vk-1.2.dist-info/top_level.txt
easy_api_vk-1.2.dist-info/RECORD
