Metadata-Version: 2.1
Name: easy-api-vk
Version: 1.2
Summary: easy-api-vk
Home-page: UNKNOWN
Author: Dimouse
Author-email: brazhenk0@icloud.com
License: UNKNOWN
Platform: UNKNOWN
Classifier: Programming Language :: Python :: 3
Classifier: License :: OSI Approved :: MIT License
Classifier: Operating System :: OS Independent
Requires-Python: >=3.6
